purplship/mappers/usps_international/__init__.py
purplship/mappers/usps_international/mapper.py
purplship/mappers/usps_international/proxy.py
purplship/mappers/usps_international/settings.py
purplship/providers/usps_international/__init__.py
purplship/providers/usps_international/error.py
purplship/providers/usps_international/pickup/__init__.py
purplship/providers/usps_international/pickup/cancel.py
purplship/providers/usps_international/pickup/create.py
purplship/providers/usps_international/pickup/update.py
purplship/providers/usps_international/rate.py
purplship/providers/usps_international/shipment/__init__.py
purplship/providers/usps_international/shipment/cancel.py
purplship/providers/usps_international/shipment/create.py
purplship/providers/usps_international/shipment/first_class_mail.py
purplship/providers/usps_international/shipment/global_express_guaranteed.py
purplship/providers/usps_international/shipment/priority_express.py
purplship/providers/usps_international/shipment/priority_mail.py
purplship/providers/usps_international/tracking.py
purplship/providers/usps_international/units.py
purplship/providers/usps_international/utils.py
purplship.usps_international-2022.2.dist-info/WHEEL
purplship.usps_international-2022.2.dist-info/METADATA
purplship.usps_international-2022.2.dist-info/RECORD
